pyscores2/RAO.py
pyscores2/__init__.py
pyscores2/_version.py
pyscores2/constants.py
pyscores2/indata.py
pyscores2/output.py
pyscores2/plotWindow.py
pyscores2/result.py
pyscores2/resultGUI.py
pyscores2/resultTreeModel.py
pyscores2/runScores2.py
pyscores2/scores1FileParser.py
pyscores2/scores2InputDialogue.py
pyscores2/testScores1Parser.py
pyscores2/waveSpectrum.py
pyscores2/waveSpectrumGUI.py
pyscores2/xml_hydrostatics.py
pyscores2/fortran/scores2.exe
pyscores2/test/S175.in
pyscores2/test/S175.out
pyscores2/test/__init__.py
pyscores2/test/temp.in
pyscores2/test/temp.out
pyscores2/test/test_run_scores2.py
pyscores2/test/test_scores2_indata.py
pyscores2/test/test_scores_file_parser.py
pyscores2/test/test_xml_hydrostatics.py
pyscores2-0.0.6.dist-info/LICENSE
pyscores2-0.0.6.dist-info/METADATA
pyscores2-0.0.6.dist-info/WHEEL
pyscores2-0.0.6.dist-info/top_level.txt
pyscores2-0.0.6.dist-info/RECORD
